Metadata-Version: 2.1
Name: the-useless-cli
Version: 1.0.0
Summary: A pretty useless CLI
Author: ItsQuadrus
Author-email: quadrus@gaboule.com
License-File: LICENSE.md
